sql_connect/MySQL.py
sql_connect/__init__.py
load_MySQL-2.0.dist-info/METADATA
load_MySQL-2.0.dist-info/WHEEL
load_MySQL-2.0.dist-info/top_level.txt
load_MySQL-2.0.dist-info/RECORD
